nr/__init__.py
nr/appfire/__init__.py
nr/appfire/py.typed
nr/appfire/application/__init__.py
nr/appfire/application/config/__init__.py
nr/appfire/application/config/logging.py
nr/appfire/awsgi/__init__.py
nr/appfire/awsgi/config.py
nr/appfire/awsgi/launcher.py
nr/appfire/awsgi/launchme.py
nr/appfire/tasks/__init__.py
nr/appfire/tasks/api.py
nr/appfire/tasks/default.py
nr/appfire/tasks/util.py
nr.appfire-0.3.0.dist-info/LICENSE.txt
nr.appfire-0.3.0.dist-info/METADATA
nr.appfire-0.3.0.dist-info/WHEEL
nr.appfire-0.3.0.dist-info/entry_points.txt
nr.appfire-0.3.0.dist-info/top_level.txt
nr.appfire-0.3.0.dist-info/RECORD
