Metadata-Version: 2.1
Name: nr.appfire
Version: 0.3.0
Summary: Appfire is a toolkit that provides utilities for quickly building configurable microservices.
Home-page: https://github.com/NiklasRosenstein/nr-python
Author: Niklas Rosenstein
Author-email: rosensteinniklas@gmail.com
License: MIT
Platform: UNKNOWN
Requires-Python: >=3.7.0,<4.0.0
Requires-Dist: PyYAML (<6.0.0,>=5.4.1)
Requires-Dist: databind.json (<2.0.0,>=1.2.3)
Requires-Dist: nr.refreshable (<1.0.0,>=0.0.2)
Requires-Dist: typing-extensions (<4.0.0,>=3.10.0.0)
